algorithm_toolkit/__init__.py
algorithm_toolkit/atk.py
algorithm_toolkit/atk_default_config.py
algorithm_toolkit/atk_test.py
algorithm_toolkit/decorators.py
algorithm_toolkit/forms.py
algorithm_toolkit/static/favicon.png
algorithm_toolkit/static/vendors/blockly/blockly_compressed.js
algorithm_toolkit/static/vendors/blockly/en.js
algorithm_toolkit/static/vendors/blockly/workspace.js
algorithm_toolkit/static/vendors/blockly/media/1x1.gif
algorithm_toolkit/static/vendors/blockly/media/click.mp3
algorithm_toolkit/static/vendors/blockly/media/click.ogg
algorithm_toolkit/static/vendors/blockly/media/click.wav
algorithm_toolkit/static/vendors/blockly/media/delete.mp3
algorithm_toolkit/static/vendors/blockly/media/delete.ogg
algorithm_toolkit/static/vendors/blockly/media/delete.wav
algorithm_toolkit/static/vendors/blockly/media/disconnect.mp3
algorithm_toolkit/static/vendors/blockly/media/disconnect.ogg
algorithm_toolkit/static/vendors/blockly/media/disconnect.wav
algorithm_toolkit/static/vendors/blockly/media/dropdown-arrow.svg
algorithm_toolkit/static/vendors/blockly/media/handclosed.cur
algorithm_toolkit/static/vendors/blockly/media/handdelete.cur
algorithm_toolkit/static/vendors/blockly/media/handopen.cur
algorithm_toolkit/static/vendors/blockly/media/pilcrow.png
algorithm_toolkit/static/vendors/blockly/media/quote0.png
algorithm_toolkit/static/vendors/blockly/media/quote1.png
algorithm_toolkit/static/vendors/blockly/media/sprites.png
algorithm_toolkit/static/vendors/blockly/media/sprites.svg
algorithm_toolkit/static/vendors/bootstrap/css/bootstrap-grid.css
algorithm_toolkit/static/vendors/bootstrap/css/bootstrap-grid.css.map
algorithm_toolkit/static/vendors/bootstrap/css/bootstrap-grid.min.css
algorithm_toolkit/static/vendors/bootstrap/css/bootstrap-grid.min.css.map
algorithm_toolkit/static/vendors/bootstrap/css/bootstrap-reboot.css
algorithm_toolkit/static/vendors/bootstrap/css/bootstrap-reboot.css.map
algorithm_toolkit-0.2.0.dist-info/LICENSE
algorithm_toolkit-0.2.0.dist-info/METADATA
algorithm_toolkit-0.2.0.dist-info/WHEEL
algorithm_toolkit-0.2.0.dist-info/entry_points.txt
algorithm_toolkit-0.2.0.dist-info/top_level.txt
algorithm_toolkit-0.2.0.dist-info/RECORD
