Metadata-Version: 2.1
Name: algorithm-toolkit
Version: 0.2.0
Summary: This project provides an easy way for researchers and developers to develop and share algorithms related to geospatial data and imagery.
Home-page: https://github.com/BeamIO-Inc/algorithm_toolkit
Author: BeamIO, Inc.
Author-email: info@beamio.net
License: MIT
Project-URL: Documentation, https://algorithm-toolkit.readthedocs.io/en/latest/index.html
Project-URL: Source Code, https://github.com/BeamIO-Inc/algorithm_toolkit
Platform: UNKNOWN
Classifier: Programming Language :: Python :: 2
Classifier: Programming Language :: Python :: 3
Classifier: License :: OSI Approved :: MIT License
Classifier: Operating System :: OS Independent
Requires-Dist: configparser
Requires-Dist: distro
Requires-Dist: flask (>=1.0)
Requires-Dist: flask-cors
Requires-Dist: flask-wtf
Requires-Dist: inflect
Requires-Dist: numpy
Requires-Dist: psutil
Requires-Dist: python-dotenv
Requires-Dist: requests
Requires-Dist: tabulate
